ProbabilisticGraphicalModelsLectureNotesCmu10708/README.md
ProbabilisticGraphicalModelsLectureNotesCmu10708/__init__.py
ProbabilisticGraphicalModelsLectureNotesCmu10708/__main__.py
ProbabilisticGraphicalModelsLectureNotesCmu10708/file.pdf
ProbabilisticGraphicalModelsLectureNotesCmu10708/index.html
probabilistic_graphical_models_lecture_notes_cmu_10_708-2024.3.2.0.dist-info/METADATA
probabilistic_graphical_models_lecture_notes_cmu_10_708-2024.3.2.0.dist-info/WHEEL
probabilistic_graphical_models_lecture_notes_cmu_10_708-2024.3.2.0.dist-info/entry_points.txt
probabilistic_graphical_models_lecture_notes_cmu_10_708-2024.3.2.0.dist-info/top_level.txt
probabilistic_graphical_models_lecture_notes_cmu_10_708-2024.3.2.0.dist-info/RECORD
